mycli_app/__init__.py
mycli_app/__main__.py
mycli_app/cli.py
mycli_app_naga-1.0.0.dist-info/licenses/LICENSE
mycli_app_naga-1.0.0.dist-info/METADATA
mycli_app_naga-1.0.0.dist-info/WHEEL
mycli_app_naga-1.0.0.dist-info/entry_points.txt
mycli_app_naga-1.0.0.dist-info/top_level.txt
mycli_app_naga-1.0.0.dist-info/RECORD
