Metadata-Version: 2.4
Name: mycli-app-naga
Version: 1.0.0
Summary: A simple CLI application similar to Azure CLI with Azure authentication capabilities
Home-page: https://github.com/naga-nandyala/mycli-app
Author: Your Name
Author-email: Your Name <your.email@example.com>
License: MIT
Project-URL: homepage, https://github.com/naga-nandyala/mycli-app
Project-URL: repository, https://github.com/naga-nandyala/mycli-app
Project-URL: documentation, https://github.com/naga-nandyala/mycli-app#readme
Project-URL: issues, https://github.com/naga-nandyala/mycli-app/issues
Keywords: cli,azure,authentication,command-line,tool
Classifier: Development Status :: 4 - Beta
Classifier: Intended Audience :: Developers
Classifier: Intended Audience :: System Administrators
Classifier: Topic :: Software Development :: Libraries :: Python Modules
Classifier: Topic :: System :: Systems Administration
Classifier: Topic :: Utilities
Classifier: License :: OSI Approved :: MIT License
Classifier: Operating System :: OS Independent
Classifier: Programming Language :: Python :: 3
Classifier: Programming Language :: Python :: 3.8
Classifier: Programming Language :: Python :: 3.9
Classifier: Programming Language :: Python :: 3.10
Classifier: Programming Language :: Python :: 3.11
Classifier: Programming Language :: Python :: 3.12
Classifier: Environment :: Console
Classifier: Typing :: Typed
Requires-Python: >=3.8
License-File: LICENSE
Requires-Dist: click>=8.0.0
Requires-Dist: colorama>=0.4.0
Provides-Extra: azure
Requires-Dist: azure-identity>=1.12.0; extra == "azure"
Requires-Dist: azure-mgmt-core>=1.3.0; extra == "azure"
Requires-Dist: azure-core>=1.24.0; extra == "azure"
Requires-Dist: msal>=1.20.0; extra == "azure"
Provides-Extra: broker
Requires-Dist: azure-identity>=1.12.0; extra == "broker"
Requires-Dist: azure-mgmt-core>=1.3.0; extra == "broker"
Requires-Dist: azure-core>=1.24.0; extra == "broker"
Requires-Dist: msal[broker]<2,>=1.20.0; extra == "broker"
Provides-Extra: dev
Requires-Dist: pytest>=7.0.0; extra == "dev"
Requires-Dist: pytest-cov>=4.0.0; extra == "dev"
Requires-Dist: black>=22.0.0; extra == "dev"
Requires-Dist: flake8>=4.0.0; extra == "dev"
Requires-Dist: mypy>=0.990; extra == "dev"
Requires-Dist: setuptools>=45.0.0; extra == "dev"
Requires-Dist: wheel>=0.36.0; extra == "dev"
Requires-Dist: twine>=4.0.0; extra == "dev"
Dynamic: author
Dynamic: home-page
Dynamic: license-file
Dynamic: requires-python
